a2p/__init__.py
a2p/tests/test_all.py
a2p-0.1.0.dist-info/METADATA
a2p-0.1.0.dist-info/WHEEL
a2p-0.1.0.dist-info/licenses/LICENSE
a2p-0.1.0.dist-info/RECORD
